{
  "$schema": "https://developer.microsoft.com/json-schemas/fabric/item/report/definition/visualContainer/2.2.0/schema.json",
  "name": "5113fda24638cd3be336",
  "position": {
    "x": 231.48936170212767,
    "y": 318.05471124620061,
    "z": 0,
    "height": 321.94528875379939,
    "width": 737.26443768996967
  },
  "visual": {
    "visualType": "clusteredColumnChart",
    "query": {
      "queryState": {
        "Category": {
          "projections": [
            {
              "field": {
                "Column": {
                  "Expression": {
                    "SourceRef": {
                      "Entity": "TablaFecha"
                    }
                  },
                  "Property": "A単o"
                }
              },
              "queryRef": "TablaFecha.A単o",
              "nativeQueryRef": "A単o",
              "active": true
            },
            {
              "field": {
                "Column": {
                  "Expression": {
                    "SourceRef": {
                      "Entity": "TablaFecha"
                    }
                  },
                  "Property": "Mes"
                }
              },
              "queryRef": "TablaFecha.Mes",
              "nativeQueryRef": "Mes",
              "active": true
            }
          ]
        },
        "Y": {
          "projections": [
            {
              "field": {
                "Aggregation": {
                  "Expression": {
                    "Column": {
                      "Expression": {
                        "SourceRef": {
                          "Entity": "InternetSales"
                        }
                      },
                      "Property": "Net Price"
                    }
                  },
                  "Function": 0
                }
              },
              "queryRef": "Sum(InternetSales.Net Price)",
              "nativeQueryRef": "Sum of Net Price"
            }
          ]
        }
      }
    },
    "drillFilterOtherVisuals": true
  },
  "filterConfig": {
    "filters": [
      {
        "name": "6b15c3c45fdc1d050f95",
        "field": {
          "Aggregation": {
            "Expression": {
              "Column": {
                "Expression": {
                  "SourceRef": {
                    "Entity": "InternetSales"
                  }
                },
                "Property": "Net Price"
              }
            },
            "Function": 0
          }
        },
        "type": "Advanced"
      },
      {
        "name": "90e3bc30e939562e1962",
        "field": {
          "Column": {
            "Expression": {
              "SourceRef": {
                "Entity": "TablaFecha"
              }
            },
            "Property": "Mes"
          }
        },
        "type": "Categorical"
      },
      {
        "name": "5d8e9615e4082fc42bda",
        "field": {
          "Column": {
            "Expression": {
              "SourceRef": {
                "Entity": "TablaFecha"
              }
            },
            "Property": "A単o"
          }
        },
        "type": "Advanced"
      }
    ]
  }
}